README.md
setup.py
ediri_vultr/__init__.py
ediri_vultr/_inputs.py
ediri_vultr/_utilities.py
ediri_vultr/bare_metal_server.py
ediri_vultr/block_storage.py
ediri_vultr/container_registry.py
ediri_vultr/database.py
ediri_vultr/database_connection_pool.py
ediri_vultr/database_connector.py
ediri_vultr/database_db.py
ediri_vultr/database_quota.py
ediri_vultr/database_replica.py
ediri_vultr/database_topic.py
ediri_vultr/database_user.py
ediri_vultr/dns_domain.py
ediri_vultr/dns_record.py
ediri_vultr/firewall_group.py
ediri_vultr/firewall_rule.py
ediri_vultr/get_account.py
ediri_vultr/get_application.py
ediri_vultr/get_backup.py
ediri_vultr/get_bare_metal_plan.py
ediri_vultr/get_bare_metal_server.py
ediri_vultr/get_block_storage.py
ediri_vultr/get_container_registry.py
ediri_vultr/get_database.py
ediri_vultr/get_dns_domain.py
ediri_vultr/get_firewall_group.py
ediri_vultr/get_inference.py
ediri_vultr/get_instance.py
ediri_vultr/get_instance_ipv4.py
ediri_vultr/get_instances.py
ediri_vultr/get_iso_private.py
ediri_vultr/get_iso_public.py
ediri_vultr/get_kubernetes.py
ediri_vultr/get_load_balancer.py
ediri_vultr/get_object_storage.py
ediri_vultr/get_object_storage_cluster.py
ediri_vultr/get_object_storage_tier.py
ediri_vultr/get_os.py
ediri_vultr/get_plan.py
ediri_vultr/get_region.py
ediri_vultr/get_reserved_ip.py
ediri_vultr/get_reverse_ipv4.py
ediri_vultr/get_reverse_ipv6.py
ediri_vultr/get_snapshot.py
ediri_vultr/get_ssh_key.py
ediri_vultr/get_startup_script.py
ediri_vultr/get_user.py
ediri_vultr/get_virtual_file_system_storage.py
ediri_vultr/get_vpc.py
ediri_vultr/get_vpc2.py
ediri_vultr/inference.py
ediri_vultr/instance.py
ediri_vultr/instance_ipv4.py
ediri_vultr/iso_private.py
ediri_vultr/kubernetes.py
ediri_vultr/kubernetes_node_pools.py
ediri_vultr/load_balancer.py
ediri_vultr/object_storage.py
ediri_vultr/outputs.py
ediri_vultr/provider.py
ediri_vultr/pulumi-plugin.json
ediri_vultr/py.typed
ediri_vultr/reserved_ip.py
ediri_vultr/reverse_ipv4.py
ediri_vultr.egg-info/PKG-INFO
ediri_vultr.egg-info/SOURCES.txt
ediri_vultr.egg-info/dependency_links.txt
ediri_vultr.egg-info/not-zip-safe
ediri_vultr.egg-info/requires.txt
ediri_vultr.egg-info/top_level.txt
