Metadata-Version: 2.1
Name: ediri-vultr
Version: 2.27.1
Summary: A Pulumi package for creating and managing Vultr cloud resources.
Home-page: https://www.pulumi.com
License: Apache-2.0
Project-URL: Repository, https://github.com/dirien/pulumi-vultr
Keywords: pulumi vultr category/utility
Platform: UNKNOWN
Requires-Python: >=3.9
